text_preprocessor/__init__.py
text_preprocessor/preprocess.py
text_to-nlp/__init__.py
text_to-nlp/preprocess.py
text_to_nlp-0.1.4.dist-info/METADATA
text_to_nlp-0.1.4.dist-info/WHEEL
text_to_nlp-0.1.4.dist-info/top_level.txt
text_to_nlp-0.1.4.dist-info/RECORD
