Metadata-Version: 2.1
Name: text-to-nlp
Version: 0.1.4
Summary: A simple text preprocessing package for NLP
Home-page: https://github.com/moraix/text-to-nlp
Author: Mehdi Omidi
Author-email: mohammadmehdiomidi95@gmail.com
Requires-Dist: nltk
Requires-Dist: scikit-learn
